LICENSE
README.rst
setup.cfg
setup.py
floss/__init__.py
floss.egg-info/PKG-INFO
floss.egg-info/SOURCES.txt
floss.egg-info/dependency_links.txt
floss.egg-info/top_level.txt
floss.egg-info/zip-safe